{"status":{"timestamp":"2026-01-11T19:13:38.396Z","error_code":0,"error_message":null,"elapsed":323,"credit_count":1,"notice":null},"data":{"active_cryptocurrencies":8991,"total_cryptocurrencies":36894,"active_market_pairs":117677,"active_exchanges":913,"total_exchanges":11705,"eth_dominance":12.146459321661,"btc_dominance":58.361367649994,"eth_dominance_yesterday":12.05806218,"btc_dominance_yesterday":58.44517892,"eth_dominance_24h_percentage_change":0.088397141661,"btc_dominance_24h_percentage_change":-0.083811270006,"defi_volume_24h":9504737956.03497,"defi_volume_24h_reported":28135832590.710857,"defi_market_cap":76794305684.14865,"defi_24h_percentage_change":2.034930731686,"stablecoin_volume_24h":50049841564.72951,"stablecoin_volume_24h_reported":238638110097.52115,"stablecoin_market_cap":285996711824.94604,"stablecoin_24h_percentage_change":0.611890128605,"derivatives_volume_24h":435835207331.3544,"derivatives_volume_24h_reported":490379445300.5674,"derivatives_24h_percentage_change":3.265869037241,"total_crypto_dex_currencies":29778763,"today_incremental_crypto_number":0,"past_24h_incremental_crypto_number":62993,"past_7d_incremental_crypto_number":338017,"past_30d_incremental_crypto_number":1516160,"today_change_percent":0.000013432393,"tracked_yearly_number":{"maxIncrementalNumber":1305553,"minIncrementalNumber":4,"maxIncrementalDate":"2025-07-08T00:00:00.000Z","minIncrementalDate":"2026-01-11T00:00:00.000Z"},"quote":{"USD":{"total_market_cap":3105491077684.5527,"total_volume_24h":52038916044.59,"total_volume_24h_reported":245359981057.35,"altcoin_volume_24h":37435868781.20341,"altcoin_volume_24h_reported":181717173266.05893,"altcoin_market_cap":1293084012499.295,"defi_volume_24h":9504737956.03497,"defi_volume_24h_reported":28135832590.710857,"defi_24h_percentage_change":2.034930731686,"defi_market_cap":76794305684.14865,"stablecoin_volume_24h":50049841564.72951,"stablecoin_volume_24h_reported":238638110097.52115,"stablecoin_24h_percentage_change":0.611890128605,"stablecoin_market_cap":285996711824.94604,"derivatives_volume_24h":435835207331.3544,"derivatives_volume_24h_reported":490379445300.5674,"derivatives_24h_percentage_change":3.265869037241,"total_market_cap_yesterday":3091653204970.522,"total_volume_24h_yesterday":51514314471.18,"total_market_cap_yesterday_percentage_change":0.4475881283121623,"total_volume_24h_yesterday_percentage_change":1.0183607775727808,"last_updated":"2026-01-11T19:11:59.999Z"}},"last_updated":"2026-01-11T19:11:59.999Z"}}