{"status":{"timestamp":"2026-01-13T23:17:53.939Z","error_code":0,"error_message":null,"elapsed":28,"credit_count":1,"notice":null},"data":{"active_cryptocurrencies":8979,"total_cryptocurrencies":36913,"active_market_pairs":117736,"active_exchanges":913,"total_exchanges":11709,"eth_dominance":12.340771282097,"btc_dominance":58.619546891676,"eth_dominance_yesterday":12.02762205,"btc_dominance_yesterday":58.69654215,"eth_dominance_24h_percentage_change":0.313149232097,"btc_dominance_24h_percentage_change":-0.076995258324,"defi_volume_24h":13481938918.396002,"defi_volume_24h_reported":43370507480.31,"defi_market_cap":79056529408.6356,"defi_24h_percentage_change":17.453723860665,"stablecoin_volume_24h":134234633558.21274,"stablecoin_volume_24h_reported":682829187211.127,"stablecoin_market_cap":286611699313.72455,"stablecoin_24h_percentage_change":25.799205743512,"derivatives_volume_24h":1193470487639.4365,"derivatives_volume_24h_reported":1262796425184.6528,"derivatives_24h_percentage_change":10.239769844564,"total_crypto_dex_currencies":29910146,"today_incremental_crypto_number":0,"past_24h_incremental_crypto_number":66740,"past_7d_incremental_crypto_number":357773,"past_30d_incremental_crypto_number":1577470,"today_change_percent":-0.000003343347,"tracked_yearly_number":{"maxIncrementalNumber":1305553,"minIncrementalNumber":0,"maxIncrementalDate":"2025-07-08T00:00:00.000Z","minIncrementalDate":"2026-01-13T00:00:00.000Z"},"quote":{"USD":{"total_market_cap":3259240099355.3677,"total_volume_24h":134301103037.19,"total_volume_24h_reported":694211471833.56,"altcoin_volume_24h":80928099179.15913,"altcoin_volume_24h_reported":419100830739.6785,"altcoin_market_cap":1348688321001.454,"defi_volume_24h":13481938918.396002,"defi_volume_24h_reported":43370507480.31,"defi_24h_percentage_change":17.453723860665,"defi_market_cap":79056529408.6356,"stablecoin_volume_24h":134234633558.21274,"stablecoin_volume_24h_reported":682829187211.127,"stablecoin_24h_percentage_change":25.799205743512,"stablecoin_market_cap":286611699313.72455,"derivatives_volume_24h":1193470487639.4365,"derivatives_volume_24h_reported":1262796425184.6528,"derivatives_24h_percentage_change":10.239769844564,"total_market_cap_yesterday":3099551792627.0854,"total_volume_24h_yesterday":108206655708.94,"total_market_cap_yesterday_percentage_change":5.15198058984312,"total_volume_24h_yesterday_percentage_change":24.1153810338989,"last_updated":"2026-01-13T23:15:59.999Z"}},"last_updated":"2026-01-13T23:15:59.999Z"}}